{"nodes": [{"id": "schemas", "label": "schemas.py", "file_type": "code", "source_file": "C:\\Users\\david\\dev\\case-adversarial-engine\\engines\\report_generation\\executive_summarizer\\schemas.py", "source_location": "L1"}, {"id": "schemas_executivesummarizerinput", "label": "ExecutiveSummarizerInput", "file_type": "code", "source_file": "C:\\Users\\david\\dev\\case-adversarial-engine\\engines\\report_generation\\executive_summarizer\\schemas.py", "source_location": "L26"}, {"id": "basemodel", "label": "BaseModel", "file_type": "code", "source_file": "", "source_location": ""}, {"id": "schemas_rationale_1", "label": "executive_summarizer \u5f15\u64ce\u4e13\u7528\u6570\u636e\u6a21\u578b\u3002\r Engine-specific schemas for executive_summarizer", "file_type": "rationale", "source_file": "C:\\Users\\david\\dev\\case-adversarial-engine\\engines\\report_generation\\executive_summarizer\\schemas.py", "source_location": "L1"}, {"id": "schemas_rationale_27", "label": "ExecutiveSummarizer \u8f93\u5165 wrapper\u3002\r \r     Args:\r         case_id:", "file_type": "rationale", "source_file": "C:\\Users\\david\\dev\\case-adversarial-engine\\engines\\report_generation\\executive_summarizer\\schemas.py", "source_location": "L27"}], "edges": [{"source": "schemas", "target": "typing", "relation": "imports_from", "confidence": "EXTRACTED", "source_file": "C:\\Users\\david\\dev\\case-adversarial-engine\\engines\\report_generation\\executive_summarizer\\schemas.py", "source_location": "L10", "weight": 1.0}, {"source": "schemas", "target": "pydantic", "relation": "imports_from", "confidence": "EXTRACTED", "source_file": "C:\\Users\\david\\dev\\case-adversarial-engine\\engines\\report_generation\\executive_summarizer\\schemas.py", "source_location": "L12", "weight": 1.0}, {"source": "schemas", "target": "engines_shared_models", "relation": "imports_from", "confidence": "EXTRACTED", "source_file": "C:\\Users\\david\\dev\\case-adversarial-engine\\engines\\report_generation\\executive_summarizer\\schemas.py", "source_location": "L14", "weight": 1.0}, {"source": "schemas", "target": "engines_simulation_run_defense_chain_schemas", "relation": "imports_from", "confidence": "EXTRACTED", "source_file": "C:\\Users\\david\\dev\\case-adversarial-engine\\engines\\report_generation\\executive_summarizer\\schemas.py", "source_location": "L23", "weight": 1.0}, {"source": "schemas", "target": "schemas_executivesummarizerinput", "relation": "contains", "confidence": "EXTRACTED", "source_file": "C:\\Users\\david\\dev\\case-adversarial-engine\\engines\\report_generation\\executive_summarizer\\schemas.py", "source_location": "L26", "weight": 1.0}, {"source": "schemas_executivesummarizerinput", "target": "basemodel", "relation": "inherits", "confidence": "EXTRACTED", "source_file": "C:\\Users\\david\\dev\\case-adversarial-engine\\engines\\report_generation\\executive_summarizer\\schemas.py", "source_location": "L26", "weight": 1.0}, {"source": "schemas_rationale_1", "target": "schemas", "relation": "rationale_for", "confidence": "EXTRACTED", "source_file": "C:\\Users\\david\\dev\\case-adversarial-engine\\engines\\report_generation\\executive_summarizer\\schemas.py", "source_location": "L1", "weight": 1.0}, {"source": "schemas_rationale_27", "target": "schemas_executivesummarizerinput", "relation": "rationale_for", "confidence": "EXTRACTED", "source_file": "C:\\Users\\david\\dev\\case-adversarial-engine\\engines\\report_generation\\executive_summarizer\\schemas.py", "source_location": "L27", "weight": 1.0}]}