{"nodes": [{"id": "generic", "label": "generic.py", "file_type": "code", "source_file": "C:\\Users\\david\\dev\\case-adversarial-engine\\engines\\case_structuring\\case_extractor\\prompts\\generic.py", "source_location": "L1"}, {"id": "generic_build_extraction_prompt", "label": "build_extraction_prompt()", "file_type": "code", "source_file": "C:\\Users\\david\\dev\\case-adversarial-engine\\engines\\case_structuring\\case_extractor\\prompts\\generic.py", "source_location": "L106"}, {"id": "generic_format_documents", "label": "format_documents()", "file_type": "code", "source_file": "C:\\Users\\david\\dev\\case-adversarial-engine\\engines\\case_structuring\\case_extractor\\prompts\\generic.py", "source_location": "L116"}, {"id": "generic_rationale_1", "label": "Generic case extraction prompt \u2014 works for all case types.\r \u901a\u7528\u6848\u4ef6\u63d0\u53d6 prompt \u2014 \u9002\u7528\u4e8e\u6240", "file_type": "rationale", "source_file": "C:\\Users\\david\\dev\\case-adversarial-engine\\engines\\case_structuring\\case_extractor\\prompts\\generic.py", "source_location": "L1"}, {"id": "generic_rationale_107", "label": "Build the extraction prompt with document text safely inserted.\r \r     Uses plac", "file_type": "rationale", "source_file": "C:\\Users\\david\\dev\\case-adversarial-engine\\engines\\case_structuring\\case_extractor\\prompts\\generic.py", "source_location": "L107"}, {"id": "generic_rationale_117", "label": "Format document texts into XML blocks for the extraction prompt.\r \r     Args:", "file_type": "rationale", "source_file": "C:\\Users\\david\\dev\\case-adversarial-engine\\engines\\case_structuring\\case_extractor\\prompts\\generic.py", "source_location": "L117"}], "edges": [{"source": "generic", "target": "generic_build_extraction_prompt", "relation": "contains", "confidence": "EXTRACTED", "source_file": "C:\\Users\\david\\dev\\case-adversarial-engine\\engines\\case_structuring\\case_extractor\\prompts\\generic.py", "source_location": "L106", "weight": 1.0}, {"source": "generic", "target": "generic_format_documents", "relation": "contains", "confidence": "EXTRACTED", "source_file": "C:\\Users\\david\\dev\\case-adversarial-engine\\engines\\case_structuring\\case_extractor\\prompts\\generic.py", "source_location": "L116", "weight": 1.0}, {"source": "generic_rationale_1", "target": "generic", "relation": "rationale_for", "confidence": "EXTRACTED", "source_file": "C:\\Users\\david\\dev\\case-adversarial-engine\\engines\\case_structuring\\case_extractor\\prompts\\generic.py", "source_location": "L1", "weight": 1.0}, {"source": "generic_rationale_107", "target": "generic_build_extraction_prompt", "relation": "rationale_for", "confidence": "EXTRACTED", "source_file": "C:\\Users\\david\\dev\\case-adversarial-engine\\engines\\case_structuring\\case_extractor\\prompts\\generic.py", "source_location": "L107", "weight": 1.0}, {"source": "generic_rationale_117", "target": "generic_format_documents", "relation": "rationale_for", "confidence": "EXTRACTED", "source_file": "C:\\Users\\david\\dev\\case-adversarial-engine\\engines\\case_structuring\\case_extractor\\prompts\\generic.py", "source_location": "L117", "weight": 1.0}]}